AUTHORS.rst
HISTORY.rst
LICENSE
MANIFEST.in
README.rst
requirements.txt
setup.cfg
setup.py
tcpwave_client/__init__.py
tcpwave_client/connector.py
tcpwave_client/exceptions.py
tcpwave_client/networks.py
tcpwave_client.egg-info/PKG-INFO
tcpwave_client.egg-info/SOURCES.txt
tcpwave_client.egg-info/dependency_links.txt
tcpwave_client.egg-info/not-zip-safe
tcpwave_client.egg-info/requires.txt
tcpwave_client.egg-info/top_level.txt
tests/__init__.py
tests/test_networks.py