Metadata-Version: 2.1
Name: tcpwave-client
Version: 1.0.2
Summary: Client for interacting with Tcpwave's IPAM
Home-page: https://github.com/TCPWAVE/tims-python-client
Author: Suman Saurabh
Author-email: saurabh.suman@tcpwave.com
License: Apache
Download-URL: https://github.com/TCPWAVE/tims-python-client/archive/master.zip
Keywords: tcpwave-client,ipam-client,tcpwave
Platform: UNKNOWN
Classifier: Development Status :: 4 - Beta
Classifier: Intended Audience :: Developers
Classifier: License :: OSI Approved :: Apache Software License
Classifier: Natural Language :: English
Classifier: Programming Language :: Python :: 3
Classifier: Programming Language :: Python :: 3.5
Classifier: Programming Language :: Python :: 3.6
Classifier: Programming Language :: Python :: 3.7
Classifier: Programming Language :: Python :: 3.8
